storm_mcp_server/__init__.py
storm_mcp_server/main.py
storm_mcp_server/core/__init__.py
storm_mcp_server/core/file_manager.py
storm_mcp_server/core/internal_api.py
storm_mcp_server/tools/__init__.py
storm_mcp_server/tools/tool_definitions.py
storm_mcp_server/tools/tool_handlers.py
storm_mcp_server/tools/tool_upload_file.py
mseep_storm_mcp_server-0.1.3.dist-info/METADATA
mseep_storm_mcp_server-0.1.3.dist-info/WHEEL
mseep_storm_mcp_server-0.1.3.dist-info/entry_points.txt
mseep_storm_mcp_server-0.1.3.dist-info/top_level.txt
mseep_storm_mcp_server-0.1.3.dist-info/RECORD
