Metadata-Version: 2.4
Name: mseep-storm-mcp-server
Version: 0.1.3
Summary: Add your description here
Author-email: mseep <support@skydeck.ai>
Requires-Python: >=3.12
Requires-Dist: fastapi>=0.115.11
Requires-Dist: mcp>=1.3.0
Requires-Dist: requests>=2.32.3
Requires-Dist: uvicorn>=0.34.0
